qurancorpus/__init__.py
qurancorpus/constants.py
qurancorpus/corpus.py
qurancorpus/data/__init__.py
qurancorpus/data/quranic-corpus-morpology.xml
qurancorpus_ziya-0.1.dist-info/METADATA
qurancorpus_ziya-0.1.dist-info/WHEEL
qurancorpus_ziya-0.1.dist-info/top_level.txt
qurancorpus_ziya-0.1.dist-info/zip-safe
qurancorpus_ziya-0.1.dist-info/RECORD
